mkdocstrings_python_generator/__init__.py
mkdocstrings_python_generator/files_generator.py
mkdocstrings_python_generator/nav_util.py
mkdocstrings_python_generator/plugin.py
mkdocstrings_python_generator-0.1.0.dist-info/METADATA
mkdocstrings_python_generator-0.1.0.dist-info/WHEEL
mkdocstrings_python_generator-0.1.0.dist-info/entry_points.txt
mkdocstrings_python_generator-0.1.0.dist-info/RECORD
