Metadata-Version: 2.1
Name: mkdocstrings-python-generator
Version: 0.1.0
Summary: Autogenerates a project's mkdocs reference documentation via mkdocstrings-python
License: MIT
Author: Philip Couling
Author-email: couling@gmail.com
Requires-Python: >=3.7,<4.0
Classifier: License :: OSI Approved :: MIT License
Classifier: Programming Language :: Python :: 3
Classifier: Programming Language :: Python :: 3.7
Classifier: Programming Language :: Python :: 3.8
Classifier: Programming Language :: Python :: 3.9
Classifier: Programming Language :: Python :: 3.10
Classifier: Programming Language :: Python :: 3.11
Requires-Dist: mkdocs (>=1.4.0,<2.0.0)
Requires-Dist: mkdocstrings-python (>=1.0.0,<2.0.0)
